rhino_gh_mcp_uv/__init__.py
rhino_gh_mcp_uv/grasshopper_tools.py
rhino_gh_mcp_uv/main.py
rhino_gh_mcp_uv/rhino_tools.py
rhino_gh_mcp_uv/server.py
rhino_gh_mcp_uv-0.1.7.dist-info/METADATA
rhino_gh_mcp_uv-0.1.7.dist-info/WHEEL
rhino_gh_mcp_uv-0.1.7.dist-info/entry_points.txt
rhino_gh_mcp_uv-0.1.7.dist-info/licenses/LICENSE
rhino_gh_mcp_uv-0.1.7.dist-info/RECORD
