Metadata-Version: 2.4
Name: rhino-gh-mcp-uv
Version: 0.1.7
Summary: Rhino and Grasshopper integration through the Model Context Protocol with uv package management
Author: Archolic
License: MIT
License-File: LICENSE
Classifier: License :: OSI Approved :: MIT License
Classifier: Operating System :: OS Independent
Classifier: Programming Language :: Python :: 3
Requires-Python: >=3.10
Requires-Dist: mcp[cli]>=1.3.0
Requires-Dist: pillow>=10.0.0
Requires-Dist: requests>=2.31.0
Requires-Dist: twine>=6.1.0
Requires-Dist: urllib3>=2.0.0
Provides-Extra: dev
Requires-Dist: python-dotenv>=1.0.0; extra == 'dev'
